{"version":"2.0.0","status":{"string":"earlydraft"},"documentation":null,"transactions":[],"workflows":[],"contracts":[{"id":"com.x.ecosystemmanagementcontracts.v2.Capability","roles":[{"id":"com.x.ecosystemmanagement.v2.PingPong.Ponger","workflowId":null,"variants":null}]},{"id":"com.x.ecosystemmanagementcontracts.v2.Pinger","roles":[{"id":"com.x.ecosystemmanagement.v2.PingPong.Pinger","workflowId":null,"variants":null}]},{"id":"com.x.ecosystemmanagementcontracts.v2.XManager","roles":[{"id":"com.x.ecosystemmanagement.v2.PingPong.Ponger","workflowId":null,"variants":null}]}]}