{"version":"1.0.2","status":{"string":"workingdraft"},"documentation":null,"transactions":[],"workflows":[],"contracts":[{"id":"com.x.comparisonshoppingcontracts.v1.ComparisonShoppingPublisher","roles":[{"id":"com.x.comparisonshopping.v1.StartDataFeed.FeedPublisher","workflowId":{"string":"com.x.comparisonshopping.v1.StartDataFeed"},"variant":null,"url":"https://api.x.com/ocl/packages/com.x.comparisonshopping.v1/StartDataFeed_FeedPublisher"},{"id":"com.x.comparisonshopping.v1.CompleteDataFeed.FeedPublisher","workflowId":{"string":"com.x.comparisonshopping.v1.CompleteDataFeed"},"variant":null,"url":"https://api.x.com/ocl/packages/com.x.comparisonshopping.v1/CompleteDataFeed_FeedPublisher"},{"id":"com.x.comparisonshopping.v1.PublishProducts.ProductFeedPublisher","workflowId":{"string":"com.x.comparisonshopping.v1.PublishProducts"},"variant":null,"url":"https://api.x.com/ocl/packages/com.x.comparisonshopping.v1/PublishProducts_ProductFeedPublisher"},{"id":"com.x.comparisonshopping.v1.PublishStoreOffers.StoreOfferFeedPublisher","workflowId":{"string":"com.x.comparisonshopping.v1.PublishStoreOffers"},"variant":null,"url":"https://api.x.com/ocl/packages/com.x.comparisonshopping.v1/PublishStoreOffers_StoreOfferFeedPublisher"},{"id":"com.x.comparisonshopping.v1.PublishStores.StoreFeedPublisher","workflowId":{"string":"com.x.comparisonshopping.v1.PublishStores"},"variant":null,"url":"https://api.x.com/ocl/packages/com.x.comparisonshopping.v1/PublishStores_StoreFeedPublisher"},{"id":"com.x.comparisonshopping.v1.ProductFeedProcessed.ProductFeedPublisher","workflowId":{"string":"com.x.comparisonshopping.v1.ProductFeedProcessed"},"variant":null,"url":"https://api.x.com/ocl/packages/com.x.comparisonshopping.v1/ProductFeedProcessed_ProductFeedPublisher"},{"id":"com.x.comparisonshopping.v1.StoreOfferFeedProcessed.StoreOfferFeedPublisher","workflowId":{"string":"com.x.comparisonshopping.v1.StoreOfferFeedProcessed"},"variant":null,"url":"https://api.x.com/ocl/packages/com.x.comparisonshopping.v1/StoreOfferFeedProcessed_StoreOfferFeedPublisher"},{"id":"com.x.comparisonshopping.v1.StoreFeedProcessed.StoreFeedPublisher","workflowId":{"string":"com.x.comparisonshopping.v1.StoreFeedProcessed"},"variant":null,"url":"https://api.x.com/ocl/packages/com.x.comparisonshopping.v1/StoreFeedProcessed_StoreFeedPublisher"}]},{"id":"com.x.comparisonshoppingcontracts.v1.ComparisonShoppingEngine","roles":[{"id":"com.x.comparisonshopping.v1.StartDataFeed.FeedManager","workflowId":{"string":"com.x.comparisonshopping.v1.StartDataFeed"},"variant":null,"url":"https://api.x.com/ocl/packages/com.x.comparisonshopping.v1/StartDataFeed_FeedManager"},{"id":"com.x.comparisonshopping.v1.CompleteDataFeed.FeedManager","workflowId":{"string":"com.x.comparisonshopping.v1.CompleteDataFeed"},"variant":null,"url":"https://api.x.com/ocl/packages/com.x.comparisonshopping.v1/CompleteDataFeed_FeedManager"},{"id":"com.x.comparisonshopping.v1.PublishProducts.ProductFeedManager","workflowId":{"string":"com.x.comparisonshopping.v1.PublishProducts"},"variant":null,"url":"https://api.x.com/ocl/packages/com.x.comparisonshopping.v1/PublishProducts_ProductFeedManager"},{"id":"com.x.comparisonshopping.v1.PublishStoreOffers.StoreOfferFeedManager","workflowId":{"string":"com.x.comparisonshopping.v1.PublishStoreOffers"},"variant":null,"url":"https://api.x.com/ocl/packages/com.x.comparisonshopping.v1/PublishStoreOffers_StoreOfferFeedManager"},{"id":"com.x.comparisonshopping.v1.PublishStores.StoreFeedManager","workflowId":{"string":"com.x.comparisonshopping.v1.PublishStores"},"variant":null,"url":"https://api.x.com/ocl/packages/com.x.comparisonshopping.v1/PublishStores_StoreFeedManager"},{"id":"com.x.comparisonshopping.v1.ProductFeedProcessed.ProductFeedManager","workflowId":{"string":"com.x.comparisonshopping.v1.ProductFeedProcessed"},"variant":null,"url":"https://api.x.com/ocl/packages/com.x.comparisonshopping.v1/ProductFeedProcessed_ProductFeedManager"},{"id":"com.x.comparisonshopping.v1.StoreOfferFeedProcessed.StoreOfferFeedManager","workflowId":{"string":"com.x.comparisonshopping.v1.StoreOfferFeedProcessed"},"variant":null,"url":"https://api.x.com/ocl/packages/com.x.comparisonshopping.v1/StoreOfferFeedProcessed_StoreOfferFeedManager"},{"id":"com.x.comparisonshopping.v1.StoreFeedProcessed.StoreFeedManager","workflowId":{"string":"com.x.comparisonshopping.v1.StoreFeedProcessed"},"variant":null,"url":"https://api.x.com/ocl/packages/com.x.comparisonshopping.v1/StoreFeedProcessed_StoreFeedManager"}]}],"bundles":[]}