{"version":"1.0.0","status":{"string":"earlydraft"},"documentation":null,"transactions":[],"workflows":[],"contracts":[{"id":"com.x.inventorycontracts.v1.InventoryConsumer","roles":[{"id":"com.x.inventory.v1.StockItemLookup.InventoryConsumer","workflowId":null,"variants":null},{"id":"com.x.inventory.v1.StockItemUpdate.InventoryObserver","workflowId":null,"variants":null},{"id":"com.x.inventory.v1.StockItemUpdated.InventoryObserver","workflowId":null,"variants":null}]},{"id":"com.x.inventorycontracts.v1.InventoryManager","roles":[{"id":"com.x.inventory.v1.StockItemLookup.InventoryManager","workflowId":null,"variants":null},{"id":"com.x.inventory.v1.StockItemUpdated.InventoryManager","workflowId":null,"variants":null}]},{"id":"com.x.inventorycontracts.v1.UpdateableInventoryManager","roles":[{"id":"com.x.inventory.v1.StockItemUpdate.InventoryManager","workflowId":null,"variants":null},{"id":"com.x.inventory.v1.StockItemUpdated.InventoryManager","workflowId":null,"variants":null}]}]}